{
  "name": "Customer",
  "fields": [
    {
      "fieldName": "id",
      "fieldType": "String"
    },
    {
      "fieldName": "email",
      "fieldType": "String"
    },
    {
      "fieldName": "lastname",
      "fieldType": "String"
    },
    {
      "fieldName": "firstname",
      "fieldType": "String"
    },
    {
      "fieldName": "phone",
      "fieldType": "String"
    },
    {
      "fieldName": "createAt",
      "fieldType": "LocalDate"
    },
    {
      "fieldName": "modifiedAt",
      "fieldType": "LocalDate"
    }
  ],
  "relationships": [],
  "entityTableName": "customer",
  "dto": "mapstruct",
  "pagination": "no",
  "service": "serviceClass",
  "jpaMetamodelFiltering": false,
  "fluentMethods": true,
  "readOnly": false,
  "embedded": false,
  "applications": ["platform"],
  "changelogDate": "20210804192623"
}
